malbrid/__init__.py
malbrid/malbrid.py
malbrid/__pycache__/__init__.cpython-310.pyc
malbrid/__pycache__/malbrid.cpython-310.pyc
malbrid-0.0.11.dist-info/LICENSE
malbrid-0.0.11.dist-info/METADATA
malbrid-0.0.11.dist-info/WHEEL
malbrid-0.0.11.dist-info/top_level.txt
malbrid-0.0.11.dist-info/RECORD
