Metadata-Version: 2.1
Name: malbrid
Version: 0.0.11
Summary: A Linear Hybrid System/Automaton Verification Library for Python
Home-page: https://github.com/tuc-es/malbrid
Author: Ruediger Ehlers
Author-email: mail2023@ruediger-ehlers.de
License: 3-Clause BSD
Classifier: Intended Audience :: Science/Research
License-File: LICENSE
